{
  "generated": "2025-06-28T07:07:51.771Z",
  "totalItems": 5,
  "summaries": {
    "CID_A_162_Athena_Commando_F_Quarrel_E5D63": {
      "name": "Cammy",
      "kidFriendlyDesc": "エピックスキンは見た目も性能も（気分的に）バッチリ！買って損なし 🎨 格ゲーファン必見！ストリートファイターコラボの激レアスキン 🥊",
      "recommendation": 5,
      "shouldBuy": true,
      "buyReason": "Cammyは今が買い時！デザインも価格もバッチリでおすすめです。",
      "targetAudience": [
        "コレクター向け",
        "ファン向け",
        "ベテラン向け"
      ]
    },
    "Character_TruckScale": {
      "name": "Iconica Prime",
      "kidFriendlyDesc": "エピックの名に恥じない完成度！これは即買い推奨です 🔥",
      "recommendation": 4,
      "shouldBuy": true,
      "buyReason": "Iconica Primeは今が買い時！デザインも価格もバッチリでおすすめです。",
      "targetAudience": [
        "コレクター向け",
        "ファン向け"
      ]
    },
    "Character_CraneAnchor": {
      "name": "Billy",
      "kidFriendlyDesc": "エピックの名に恥じない完成度！これは即買い推奨です 🔥",
      "recommendation": 4,
      "shouldBuy": true,
      "buyReason": "Billyは今が買い時！デザインも価格もバッチリでおすすめです。",
      "targetAudience": [
        "コレクター向け",
        "ファン向け"
      ]
    },
    "CID_A_161_Athena_Commando_M_Quarrel_SLXQG": {
      "name": "Guile",
      "kidFriendlyDesc": "人気の高いエピックランク！デザインが凝っててお気に入りになること間違いなし 💜 格ゲーファン必見！ストリートファイターコラボの激レアスキン 🥊",
      "recommendation": 5,
      "shouldBuy": true,
      "buyReason": "Guileは今が買い時！デザインも価格もバッチリでおすすめです。",
      "targetAudience": [
        "コレクター向け",
        "ファン向け",
        "ベテラン向け"
      ]
    },
    "Character_ThickWatch": {
      "name": "Flightalis",
      "kidFriendlyDesc": "エピックスキンは見た目も性能も（気分的に）バッチリ！買って損なし 🎨",
      "recommendation": 5,
      "shouldBuy": true,
      "buyReason": "Flightalisは今が買い時！デザインも価格もバッチリでおすすめです。",
      "targetAudience": [
        "コレクター向け",
        "初心者向け",
        "ファン向け"
      ]
    }
  }
}